cosmics/__init__.py
cosmics/domain/__init__.py
cosmics/domain/commands.py
cosmics/domain/events.py
cosmics/domain/model.py
cosmics/repository/__init__.py
cosmics/repository/database.py
cosmics/repository/postgresql/__init__.py
cosmics/repository/postgresql/_query_builder.py
cosmics/repository/postgresql/database.py
cosmics/repository/postgresql/repository.py
cosmics/repository/repository.py
cosmics/service_layer/__init__.py
cosmics/service_layer/messagebus.py
cosmics/service_layer/unit_of_work.py
cosmics/testing/__init__.py
cosmics/testing/fakes/__init__.py
cosmics/testing/fakes/domain/__init__.py
cosmics/testing/fakes/domain/model.py
cosmics/testing/fakes/repository/__init__.py
cosmics/testing/fakes/repository/database.py
cosmics/testing/fakes/repository/postgresql/__init__.py
cosmics/testing/fakes/repository/postgresql/database.py
cosmics/testing/fakes/repository/postgresql/repository.py
cosmics/testing/fakes/repository/repository.py
cosmics/testing/fakes/service_layer/__init__.py
cosmics/testing/fakes/service_layer/unit_of_work.py
cosmics-0.1.2.dist-info/WHEEL
cosmics-0.1.2.dist-info/METADATA
cosmics-0.1.2.dist-info/RECORD
